glnext.cpython-37m-x86_64-linux-gnu.so
glnext-0.8.1.dist-info/LICENSE
glnext-0.8.1.dist-info/top_level.txt
glnext-0.8.1.dist-info/RECORD
glnext-0.8.1.dist-info/WHEEL
glnext-0.8.1.dist-info/METADATA
