Metadata-Version: 2.1
Name: glnext
Version: 0.8.1
Summary: UNKNOWN
Home-page: https://github.com/glnext/glnext/
Author: Szabolcs Dombi
Author-email: cprogrammer1994@gmail.com
License: MIT
Platform: UNKNOWN
